strstyle/__init__.py
strstyle/ansi.py
strstyle/styled_string.py
strstyle/styled_string_builder.py
strstyle-1.2.7.dist-info/LICENSE.txt
strstyle-1.2.7.dist-info/METADATA
strstyle-1.2.7.dist-info/WHEEL
strstyle-1.2.7.dist-info/top_level.txt
strstyle-1.2.7.dist-info/RECORD
