Metadata-Version: 2.1
Name: strstyle
Version: 1.2.7
Summary: python package to handle colorful outputs
Home-page: https://github.com/limittman
Author: limittman
Author-email: limitmann120@gmail.com
Classifier: Programming Language :: Python :: 3
Classifier: License :: OSI Approved :: MIT License
Classifier: Operating System :: OS Independent
Requires-Python: >=3.7
License-File: LICENSE.txt
